[
  {
    "game_id": "13184",
    "date": "2025-10-31",
    "time": "",
    "game_name": "LG @ HAN",
    "home_team": "HAN",
    "away_team": "LG",
    "full_game_pick": "LG",
    "full_game_confidence": 66,
    "full_game_tier": "PREMIUM",
    "q1_pick": "YRFI",
    "q1_confidence": 61,
    "q1_action": "JUGAR",
    "spread_pick": "LG ML",
    "spread_market": "ML",
    "total_pick": "UNDER",
    "odds_over_under": 0.0,
    "closing_moneyline_odds": null,
    "home_moneyline_odds": null,
    "away_moneyline_odds": null,
    "closing_total_odds": null,
    "odds_data_quality": "fallback",
    "assists_pick": "LG F5",
    "extra_f5_confidence": 53,
    "extra_f5_tier": "PASS"
  }
]