[
  {
    "game_id": "725080",
    "date": "2025-02-01",
    "home_team": "AME",
    "away_team": "JUA",
    "odds_over_under": 0.0,
    "closing_moneyline_odds": null,
    "home_moneyline_odds": null,
    "away_moneyline_odds": null,
    "closing_total_odds": null,
    "odds_data_quality": "fallback",
    "full_game_pick": "AME",
    "full_game_confidence": 99,
    "full_game_tier": "ELITE",
    "recommended_pick": "AME",
    "recommended_confidence": 90,
    "base_probability": 0.988026,
    "adjusted_probability": 0.904762,
    "adjustment_amount": -0.083264,
    "adjustment_breakdown": [
      {
        "event_name": "home_good_form",
        "direction": "positive",
        "strength": 0.02,
        "sign": 1.0,
        "contribution": 0.012599999999999998,
        "explanation": "Local con buena forma reciente.",
        "category": "form"
      },
      {
        "event_name": "home_team_hot_attack",
        "direction": "positive",
        "strength": 0.025,
        "sign": 1.0,
        "contribution": 0.01575,
        "explanation": "Ataque local encendido.",
        "category": "attack_defense"
      },
      {
        "event_name": "away_team_cold_attack",
        "direction": "negative",
        "strength": 0.02,
        "sign": 1.0,
        "contribution": 0.012599999999999998,
        "explanation": "Ataque visitante en baja.",
        "category": "attack_defense"
      },
      {
        "event_name": "low_h2h_sample",
        "direction": "neutral",
        "strength": 0.0,
        "sign": 0.0,
        "contribution": 0.0,
        "explanation": "Muestra H2H baja; peso H2H reducido.",
        "category": "reliability"
      }
    ],
    "detected_events": [
      {
        "event_name": "home_good_form",
        "direction": "positive",
        "strength": 0.02,
        "explanation": "Local con buena forma reciente.",
        "category": "form"
      },
      {
        "event_name": "home_team_hot_attack",
        "direction": "positive",
        "strength": 0.025,
        "explanation": "Ataque local encendido.",
        "category": "attack_defense"
      },
      {
        "event_name": "away_team_cold_attack",
        "direction": "negative",
        "strength": 0.02,
        "explanation": "Ataque visitante en baja.",
        "category": "attack_defense"
      },
      {
        "event_name": "low_h2h_sample",
        "direction": "neutral",
        "strength": 0.0,
        "explanation": "Muestra H2H baja; peso H2H reducido.",
        "category": "reliability"
      }
    ],
    "total_pick": "OVER 2.5",
    "total_recommended_pick": "OVER 2.5",
    "total_base_probability": 0.968458,
    "total_adjusted_probability": 0.95,
    "total_adjustment_amount": -0.018458,
    "total_adjustment_breakdown": [
      {
        "event_name": "home_good_form",
        "direction": "positive",
        "strength": 0.02,
        "sign": 1.0,
        "contribution": 0.013999999999999999,
        "explanation": "Local con buena forma reciente.",
        "category": "form"
      },
      {
        "event_name": "home_team_hot_attack",
        "direction": "positive",
        "strength": 0.025,
        "sign": 1.0,
        "contribution": 0.017499999999999998,
        "explanation": "Ataque local encendido.",
        "category": "attack_defense"
      },
      {
        "event_name": "away_team_cold_attack",
        "direction": "negative",
        "strength": 0.02,
        "sign": -1.0,
        "contribution": -0.013999999999999999,
        "explanation": "Ataque visitante en baja.",
        "category": "attack_defense"
      },
      {
        "event_name": "low_h2h_sample",
        "direction": "neutral",
        "strength": 0.0,
        "sign": 0.0,
        "contribution": 0.0,
        "explanation": "Muestra H2H baja; peso H2H reducido.",
        "category": "reliability"
      }
    ],
    "btts_pick": "BTTS NO",
    "btts_recommended_pick": "BTTS NO",
    "btts_base_probability": 0.017161,
    "btts_adjusted_probability": 0.05,
    "btts_adjustment_amount": 0.032839,
    "btts_adjustment_breakdown": [
      {
        "event_name": "home_good_form",
        "direction": "positive",
        "strength": 0.02,
        "sign": 1.0,
        "contribution": 0.013999999999999999,
        "explanation": "Local con buena forma reciente.",
        "category": "form"
      },
      {
        "event_name": "home_team_hot_attack",
        "direction": "positive",
        "strength": 0.025,
        "sign": 1.0,
        "contribution": 0.017499999999999998,
        "explanation": "Ataque local encendido.",
        "category": "attack_defense"
      },
      {
        "event_name": "away_team_cold_attack",
        "direction": "negative",
        "strength": 0.02,
        "sign": -1.0,
        "contribution": -0.013999999999999999,
        "explanation": "Ataque visitante en baja.",
        "category": "attack_defense"
      },
      {
        "event_name": "low_h2h_sample",
        "direction": "neutral",
        "strength": 0.0,
        "sign": 0.0,
        "contribution": 0.0,
        "explanation": "Muestra H2H baja; peso H2H reducido.",
        "category": "reliability"
      }
    ],
    "corners_pick": "UNDER 9.5",
    "corners_recommended_pick": "UNDER 9.5",
    "corners_base_probability": 0.082031,
    "corners_adjusted_probability": 0.082031,
    "corners_adjustment_amount": 0.0,
    "corners_adjustment_breakdown": [],
    "actual_home_score": 4,
    "actual_away_score": 0,
    "actual_result": "AME",
    "correct_full_game_base": 1,
    "correct_full_game_adjusted": 1,
    "correct_total_base": 1,
    "correct_total_adjusted": 1,
    "correct_btts_base": 1,
    "correct_btts_adjusted": 1,
    "correct_corners_base": 1,
    "correct_corners_adjusted": 1,
    "actual_full_game_class": 1,
    "fg_prob_away_base": 0.004508783781828607,
    "fg_prob_home_base": 0.9880263921774514,
    "fg_prob_draw_base": 0.007464811933526647,
    "fg_prob_away_adjusted": 0.047619047619047616,
    "fg_prob_home_adjusted": 0.9047619047619047,
    "fg_prob_draw_adjusted": 0.047619047619047616,
    "over_actual": 1,
    "btts_actual": 0,
    "corners_actual": 0
  },
  {
    "game_id": "725081",
    "date": "2025-02-01",
    "home_team": "GDL",
    "away_team": "QRO",
    "odds_over_under": 0.0,
    "closing_moneyline_odds": null,
    "home_moneyline_odds": null,
    "away_moneyline_odds": null,
    "closing_total_odds": null,
    "odds_data_quality": "fallback",
    "full_game_pick": "DRAW",
    "full_game_confidence": 92,
    "full_game_tier": "ELITE",
    "recommended_pick": "DRAW",
    "recommended_confidence": 90,
    "base_probability": 0.920029,
    "adjusted_probability": 0.901964,
    "adjustment_amount": -0.018065,
    "adjustment_breakdown": [
      {
        "event_name": "low_h2h_sample",
        "direction": "neutral",
        "strength": 0.0,
        "sign": 0.0,
        "contribution": 0.0,
        "explanation": "Muestra H2H baja; peso H2H reducido.",
        "category": "reliability"
      }
    ],
    "detected_events": [
      {
        "event_name": "low_h2h_sample",
        "direction": "neutral",
        "strength": 0.0,
        "explanation": "Muestra H2H baja; peso H2H reducido.",
        "category": "reliability"
      }
    ],
    "total_pick": "UNDER 2.5",
    "total_recommended_pick": "UNDER 2.5",
    "total_base_probability": 0.052155,
    "total_adjusted_probability": 0.052155,
    "total_adjustment_amount": 0.0,
    "total_adjustment_breakdown": [
      {
        "event_name": "low_h2h_sample",
        "direction": "neutral",
        "strength": 0.0,
        "sign": 0.0,
        "contribution": 0.0,
        "explanation": "Muestra H2H baja; peso H2H reducido.",
        "category": "reliability"
      }
    ],
    "btts_pick": "BTTS YES",
    "btts_recommended_pick": "BTTS YES",
    "btts_base_probability": 0.937314,
    "btts_adjusted_probability": 0.937314,
    "btts_adjustment_amount": 0.0,
    "btts_adjustment_breakdown": [
      {
        "event_name": "low_h2h_sample",
        "direction": "neutral",
        "strength": 0.0,
        "sign": 0.0,
        "contribution": 0.0,
        "explanation": "Muestra H2H baja; peso H2H reducido.",
        "category": "reliability"
      }
    ],
    "corners_pick": "OVER 9.5",
    "corners_recommended_pick": "OVER 9.5",
    "corners_base_probability": 0.994779,
    "corners_adjusted_probability": 0.994779,
    "corners_adjustment_amount": 0.0,
    "corners_adjustment_breakdown": [],
    "actual_home_score": 1,
    "actual_away_score": 1,
    "actual_result": "DRAW",
    "correct_full_game_base": 1,
    "correct_full_game_adjusted": 1,
    "correct_total_base": 1,
    "correct_total_adjusted": 1,
    "correct_btts_base": 1,
    "correct_btts_adjusted": 1,
    "correct_corners_base": 1,
    "correct_corners_adjusted": 1,
    "actual_full_game_class": 2,
    "fg_prob_away_base": 0.03476062803853438,
    "fg_prob_home_base": 0.04521072007220676,
    "fg_prob_draw_base": 0.9200286456804418,
    "fg_prob_away_adjusted": 0.04901823121511058,
    "fg_prob_home_adjusted": 0.04901823121511058,
    "fg_prob_draw_adjusted": 0.9019635375697788,
    "over_actual": 0,
    "btts_actual": 1,
    "corners_actual": 1
  },
  {
    "game_id": "725082",
    "date": "2025-02-01",
    "home_team": "MTY",
    "away_team": "NEC",
    "odds_over_under": 0.0,
    "closing_moneyline_odds": null,
    "home_moneyline_odds": null,
    "away_moneyline_odds": null,
    "closing_total_odds": null,
    "odds_data_quality": "fallback",
    "full_game_pick": "MTY",
    "full_game_confidence": 94,
    "full_game_tier": "ELITE",
    "recommended_pick": "MTY",
    "recommended_confidence": 90,
    "base_probability": 0.942643,
    "adjusted_probability": 0.897274,
    "adjustment_amount": -0.045369,
    "adjustment_breakdown": [
      {
        "event_name": "away_team_hot_attack",
        "direction": "positive",
        "strength": 0.025,
        "sign": -1.0,
        "contribution": -0.01575,
        "explanation": "Ataque visitante encendido.",
        "category": "attack_defense"
      },
      {
        "event_name": "home_team_weak_defense",
        "direction": "negative",
        "strength": 0.02,
        "sign": -1.0,
        "contribution": -0.012599999999999998,
        "explanation": "Defensa local vulnerable.",
        "category": "attack_defense"
      },
      {
        "event_name": "away_team_weak_defense",
        "direction": "negative",
        "strength": 0.02,
        "sign": 1.0,
        "contribution": 0.012599999999999998,
        "explanation": "Defensa visitante vulnerable.",
        "category": "attack_defense"
      },
      {
        "event_name": "both_teams_btts_trend",
        "direction": "positive",
        "strength": 0.03,
        "sign": 0.0,
        "contribution": 0.0,
        "explanation": "Ambos con tendencia BTTS.",
        "category": "trend"
      },
      {
        "event_name": "low_h2h_sample",
        "direction": "neutral",
        "strength": 0.0,
        "sign": 0.0,
        "contribution": 0.0,
        "explanation": "Muestra H2H baja; peso H2H reducido.",
        "category": "reliability"
      }
    ],
    "detected_events": [
      {
        "event_name": "away_team_hot_attack",
        "direction": "positive",
        "strength": 0.025,
        "explanation": "Ataque visitante encendido.",
        "category": "attack_defense"
      },
      {
        "event_name": "home_team_weak_defense",
        "direction": "negative",
        "strength": 0.02,
        "explanation": "Defensa local vulnerable.",
        "category": "attack_defense"
      },
      {
        "event_name": "away_team_weak_defense",
        "direction": "negative",
        "strength": 0.02,
        "explanation": "Defensa visitante vulnerable.",
        "category": "attack_defense"
      },
      {
        "event_name": "both_teams_btts_trend",
        "direction": "positive",
        "strength": 0.03,
        "explanation": "Ambos con tendencia BTTS.",
        "category": "trend"
      },
      {
        "event_name": "low_h2h_sample",
        "direction": "neutral",
        "strength": 0.0,
        "explanation": "Muestra H2H baja; peso H2H reducido.",
        "category": "reliability"
      }
    ],
    "total_pick": "UNDER 2.5",
    "total_recommended_pick": "UNDER 2.5",
    "total_base_probability": 0.111024,
    "total_adjusted_probability": 0.168546,
    "total_adjustment_amount": 0.057523,
    "total_adjustment_breakdown": [
      {
        "event_name": "away_team_hot_attack",
        "direction": "positive",
        "strength": 0.025,
        "sign": 1.0,
        "contribution": 0.017499999999999998,
        "explanation": "Ataque visitante encendido.",
        "category": "attack_defense"
      },
      {
        "event_name": "home_team_weak_defense",
        "direction": "negative",
        "strength": 0.02,
        "sign": 1.0,
        "contribution": 0.013999999999999999,
        "explanation": "Defensa local vulnerable.",
        "category": "attack_defense"
      },
      {
        "event_name": "away_team_weak_defense",
        "direction": "negative",
        "strength": 0.02,
        "sign": 1.0,
        "contribution": 0.013999999999999999,
        "explanation": "Defensa visitante vulnerable.",
        "category": "attack_defense"
      },
      {
        "event_name": "both_teams_btts_trend",
        "direction": "positive",
        "strength": 0.03,
        "sign": 1.0,
        "contribution": 0.020999999999999998,
        "explanation": "Ambos con tendencia BTTS.",
        "category": "trend"
      },
      {
        "event_name": "low_h2h_sample",
        "direction": "neutral",
        "strength": 0.0,
        "sign": 0.0,
        "contribution": 0.0,
        "explanation": "Muestra H2H baja; peso H2H reducido.",
        "category": "reliability"
      }
    ],
    "btts_pick": "BTTS NO",
    "btts_recommended_pick": "BTTS NO",
    "btts_base_probability": 0.075041,
    "btts_adjusted_probability": 0.132563,
    "btts_adjustment_amount": 0.057522,
    "btts_adjustment_breakdown": [
      {
        "event_name": "away_team_hot_attack",
        "direction": "positive",
        "strength": 0.025,
        "sign": 1.0,
        "contribution": 0.017499999999999998,
        "explanation": "Ataque visitante encendido.",
        "category": "attack_defense"
      },
      {
        "event_name": "home_team_weak_defense",
        "direction": "negative",
        "strength": 0.02,
        "sign": 1.0,
        "contribution": 0.013999999999999999,
        "explanation": "Defensa local vulnerable.",
        "category": "attack_defense"
      },
      {
        "event_name": "away_team_weak_defense",
        "direction": "negative",
        "strength": 0.02,
        "sign": 1.0,
        "contribution": 0.013999999999999999,
        "explanation": "Defensa visitante vulnerable.",
        "category": "attack_defense"
      },
      {
        "event_name": "both_teams_btts_trend",
        "direction": "positive",
        "strength": 0.03,
        "sign": 1.0,
        "contribution": 0.020999999999999998,
        "explanation": "Ambos con tendencia BTTS.",
        "category": "trend"
      },
      {
        "event_name": "low_h2h_sample",
        "direction": "neutral",
        "strength": 0.0,
        "sign": 0.0,
        "contribution": 0.0,
        "explanation": "Muestra H2H baja; peso H2H reducido.",
        "category": "reliability"
      }
    ],
    "corners_pick": "OVER 9.5",
    "corners_recommended_pick": "OVER 9.5",
    "corners_base_probability": 0.927542,
    "corners_adjusted_probability": 0.927542,
    "corners_adjustment_amount": 0.0,
    "corners_adjustment_breakdown": [],
    "actual_home_score": 1,
    "actual_away_score": 0,
    "actual_result": "MTY",
    "correct_full_game_base": 1,
    "correct_full_game_adjusted": 1,
    "correct_total_base": 1,
    "correct_total_adjusted": 1,
    "correct_btts_base": 1,
    "correct_btts_adjusted": 1,
    "correct_corners_base": 1,
    "correct_corners_adjusted": 1,
    "actual_full_game_class": 1,
    "fg_prob_away_base": 0.04273685716025447,
    "fg_prob_home_base": 0.9426431670142493,
    "fg_prob_draw_base": 0.014619959061689966,
    "fg_prob_away_adjusted": 0.054434705947886255,
    "fg_prob_home_adjusted": 0.8972738466293528,
    "fg_prob_draw_adjusted": 0.048291447422760946,
    "over_actual": 0,
    "btts_actual": 0,
    "corners_actual": 1
  },
  {
    "game_id": "725083",
    "date": "2025-02-01",
    "home_team": "PAC",
    "away_team": "ATS",
    "odds_over_under": 0.0,
    "closing_moneyline_odds": null,
    "home_moneyline_odds": null,
    "away_moneyline_odds": null,
    "closing_total_odds": null,
    "odds_data_quality": "fallback",
    "full_game_pick": "DRAW",
    "full_game_confidence": 93,
    "full_game_tier": "ELITE",
    "recommended_pick": "DRAW",
    "recommended_confidence": 88,
    "base_probability": 0.929182,
    "adjusted_probability": 0.88102,
    "adjustment_amount": -0.048161,
    "adjustment_breakdown": [
      {
        "event_name": "home_good_form",
        "direction": "positive",
        "strength": 0.02,
        "sign": 0.0,
        "contribution": 0.0,
        "explanation": "Local con buena forma reciente.",
        "category": "form"
      },
      {
        "event_name": "home_team_hot_attack",
        "direction": "positive",
        "strength": 0.025,
        "sign": -0.5,
        "contribution": -0.004200000000000001,
        "explanation": "Ataque local encendido.",
        "category": "attack_defense"
      },
      {
        "event_name": "both_teams_btts_trend",
        "direction": "positive",
        "strength": 0.03,
        "sign": 0.0,
        "contribution": 0.0,
        "explanation": "Ambos con tendencia BTTS.",
        "category": "trend"
      },
      {
        "event_name": "low_recent_sample",
        "direction": "neutral",
        "strength": 0.0,
        "sign": 0.0,
        "contribution": 0.0,
        "explanation": "Muestra reciente baja; ajustes moderados.",
        "category": "reliability"
      },
      {
        "event_name": "low_h2h_sample",
        "direction": "neutral",
        "strength": 0.0,
        "sign": 0.0,
        "contribution": 0.0,
        "explanation": "Muestra H2H baja; peso H2H reducido.",
        "category": "reliability"
      }
    ],
    "detected_events": [
      {
        "event_name": "home_good_form",
        "direction": "positive",
        "strength": 0.02,
        "explanation": "Local con buena forma reciente.",
        "category": "form"
      },
      {
        "event_name": "home_team_hot_attack",
        "direction": "positive",
        "strength": 0.025,
        "explanation": "Ataque local encendido.",
        "category": "attack_defense"
      },
      {
        "event_name": "both_teams_btts_trend",
        "direction": "positive",
        "strength": 0.03,
        "explanation": "Ambos con tendencia BTTS.",
        "category": "trend"
      },
      {
        "event_name": "low_recent_sample",
        "direction": "neutral",
        "strength": 0.0,
        "explanation": "Muestra reciente baja; ajustes moderados.",
        "category": "reliability"
      },
      {
        "event_name": "low_h2h_sample",
        "direction": "neutral",
        "strength": 0.0,
        "explanation": "Muestra H2H baja; peso H2H reducido.",
        "category": "reliability"
      }
    ],
    "total_pick": "UNDER 2.5",
    "total_recommended_pick": "UNDER 2.5",
    "total_base_probability": 0.160925,
    "total_adjusted_probability": 0.184204,
    "total_adjustment_amount": 0.023279,
    "total_adjustment_breakdown": [
      {
        "event_name": "home_good_form",
        "direction": "positive",
        "strength": 0.02,
        "sign": 1.0,
        "contribution": 0.0084,
        "explanation": "Local con buena forma reciente.",
        "category": "form"
      },
      {
        "event_name": "home_team_hot_attack",
        "direction": "positive",
        "strength": 0.025,
        "sign": 1.0,
        "contribution": 0.0105,
        "explanation": "Ataque local encendido.",
        "category": "attack_defense"
      },
      {
        "event_name": "both_teams_btts_trend",
        "direction": "positive",
        "strength": 0.03,
        "sign": 1.0,
        "contribution": 0.012599999999999998,
        "explanation": "Ambos con tendencia BTTS.",
        "category": "trend"
      },
      {
        "event_name": "low_recent_sample",
        "direction": "neutral",
        "strength": 0.0,
        "sign": 0.0,
        "contribution": 0.0,
        "explanation": "Muestra reciente baja; ajustes moderados.",
        "category": "reliability"
      },
      {
        "event_name": "low_h2h_sample",
        "direction": "neutral",
        "strength": 0.0,
        "sign": 0.0,
        "contribution": 0.0,
        "explanation": "Muestra H2H baja; peso H2H reducido.",
        "category": "reliability"
      }
    ],
    "btts_pick": "BTTS NO",
    "btts_recommended_pick": "BTTS NO",
    "btts_base_probability": 0.100155,
    "btts_adjusted_probability": 0.123434,
    "btts_adjustment_amount": 0.023279,
    "btts_adjustment_breakdown": [
      {
        "event_name": "home_good_form",
        "direction": "positive",
        "strength": 0.02,
        "sign": 1.0,
        "contribution": 0.0084,
        "explanation": "Local con buena forma reciente.",
        "category": "form"
      },
      {
        "event_name": "home_team_hot_attack",
        "direction": "positive",
        "strength": 0.025,
        "sign": 1.0,
        "contribution": 0.0105,
        "explanation": "Ataque local encendido.",
        "category": "attack_defense"
      },
      {
        "event_name": "both_teams_btts_trend",
        "direction": "positive",
        "strength": 0.03,
        "sign": 1.0,
        "contribution": 0.012599999999999998,
        "explanation": "Ambos con tendencia BTTS.",
        "category": "trend"
      },
      {
        "event_name": "low_recent_sample",
        "direction": "neutral",
        "strength": 0.0,
        "sign": 0.0,
        "contribution": 0.0,
        "explanation": "Muestra reciente baja; ajustes moderados.",
        "category": "reliability"
      },
      {
        "event_name": "low_h2h_sample",
        "direction": "neutral",
        "strength": 0.0,
        "sign": 0.0,
        "contribution": 0.0,
        "explanation": "Muestra H2H baja; peso H2H reducido.",
        "category": "reliability"
      }
    ],
    "corners_pick": "UNDER 9.5",
    "corners_recommended_pick": "UNDER 9.5",
    "corners_base_probability": 0.026891,
    "corners_adjusted_probability": 0.026891,
    "corners_adjustment_amount": 0.0,
    "corners_adjustment_breakdown": [],
    "actual_home_score": 0,
    "actual_away_score": 0,
    "actual_result": "DRAW",
    "correct_full_game_base": 1,
    "correct_full_game_adjusted": 1,
    "correct_total_base": 1,
    "correct_total_adjusted": 1,
    "correct_btts_base": 1,
    "correct_btts_adjusted": 1,
    "correct_corners_base": 1,
    "correct_corners_adjusted": 1,
    "actual_full_game_class": 2,
    "fg_prob_away_base": 0.008324175503106363,
    "fg_prob_home_base": 0.06249426897009978,
    "fg_prob_draw_base": 0.9291815722906002,
    "fg_prob_away_adjusted": 0.04756729298809859,
    "fg_prob_home_adjusted": 0.07141245252564879,
    "fg_prob_draw_adjusted": 0.8810202544862525,
    "over_actual": 0,
    "btts_actual": 0,
    "corners_actual": 0
  },
  {
    "game_id": "725084",
    "date": "2025-02-01",
    "home_team": "TOL",
    "away_team": "UANL",
    "odds_over_under": 0.0,
    "closing_moneyline_odds": null,
    "home_moneyline_odds": null,
    "away_moneyline_odds": null,
    "closing_total_odds": null,
    "odds_data_quality": "fallback",
    "full_game_pick": "TOL",
    "full_game_confidence": 94,
    "full_game_tier": "ELITE",
    "recommended_pick": "TOL",
    "recommended_confidence": 88,
    "base_probability": 0.937767,
    "adjusted_probability": 0.882996,
    "adjustment_amount": -0.054771,
    "adjustment_breakdown": [
      {
        "event_name": "away_good_form",
        "direction": "positive",
        "strength": 0.02,
        "sign": -1.0,
        "contribution": -0.012599999999999998,
        "explanation": "Visita con buena forma reciente.",
        "category": "form"
      },
      {
        "event_name": "away_team_hot_attack",
        "direction": "positive",
        "strength": 0.025,
        "sign": -1.0,
        "contribution": -0.01575,
        "explanation": "Ataque visitante encendido.",
        "category": "attack_defense"
      },
      {
        "event_name": "both_teams_btts_trend",
        "direction": "positive",
        "strength": 0.03,
        "sign": 0.0,
        "contribution": 0.0,
        "explanation": "Ambos con tendencia BTTS.",
        "category": "trend"
      },
      {
        "event_name": "low_h2h_sample",
        "direction": "neutral",
        "strength": 0.0,
        "sign": 0.0,
        "contribution": 0.0,
        "explanation": "Muestra H2H baja; peso H2H reducido.",
        "category": "reliability"
      }
    ],
    "detected_events": [
      {
        "event_name": "away_good_form",
        "direction": "positive",
        "strength": 0.02,
        "explanation": "Visita con buena forma reciente.",
        "category": "form"
      },
      {
        "event_name": "away_team_hot_attack",
        "direction": "positive",
        "strength": 0.025,
        "explanation": "Ataque visitante encendido.",
        "category": "attack_defense"
      },
      {
        "event_name": "both_teams_btts_trend",
        "direction": "positive",
        "strength": 0.03,
        "explanation": "Ambos con tendencia BTTS.",
        "category": "trend"
      },
      {
        "event_name": "low_h2h_sample",
        "direction": "neutral",
        "strength": 0.0,
        "explanation": "Muestra H2H baja; peso H2H reducido.",
        "category": "reliability"
      }
    ],
    "total_pick": "UNDER 2.5",
    "total_recommended_pick": "UNDER 2.5",
    "total_base_probability": 0.047024,
    "total_adjusted_probability": 0.092436,
    "total_adjustment_amount": 0.045412,
    "total_adjustment_breakdown": [
      {
        "event_name": "away_good_form",
        "direction": "positive",
        "strength": 0.02,
        "sign": 1.0,
        "contribution": 0.013999999999999999,
        "explanation": "Visita con buena forma reciente.",
        "category": "form"
      },
      {
        "event_name": "away_team_hot_attack",
        "direction": "positive",
        "strength": 0.025,
        "sign": 1.0,
        "contribution": 0.017499999999999998,
        "explanation": "Ataque visitante encendido.",
        "category": "attack_defense"
      },
      {
        "event_name": "both_teams_btts_trend",
        "direction": "positive",
        "strength": 0.03,
        "sign": 1.0,
        "contribution": 0.020999999999999998,
        "explanation": "Ambos con tendencia BTTS.",
        "category": "trend"
      },
      {
        "event_name": "low_h2h_sample",
        "direction": "neutral",
        "strength": 0.0,
        "sign": 0.0,
        "contribution": 0.0,
        "explanation": "Muestra H2H baja; peso H2H reducido.",
        "category": "reliability"
      }
    ],
    "btts_pick": "BTTS NO",
    "btts_recommended_pick": "BTTS NO",
    "btts_base_probability": 0.055168,
    "btts_adjusted_probability": 0.100581,
    "btts_adjustment_amount": 0.045412,
    "btts_adjustment_breakdown": [
      {
        "event_name": "away_good_form",
        "direction": "positive",
        "strength": 0.02,
        "sign": 1.0,
        "contribution": 0.013999999999999999,
        "explanation": "Visita con buena forma reciente.",
        "category": "form"
      },
      {
        "event_name": "away_team_hot_attack",
        "direction": "positive",
        "strength": 0.025,
        "sign": 1.0,
        "contribution": 0.017499999999999998,
        "explanation": "Ataque visitante encendido.",
        "category": "attack_defense"
      },
      {
        "event_name": "both_teams_btts_trend",
        "direction": "positive",
        "strength": 0.03,
        "sign": 1.0,
        "contribution": 0.020999999999999998,
        "explanation": "Ambos con tendencia BTTS.",
        "category": "trend"
      },
      {
        "event_name": "low_h2h_sample",
        "direction": "neutral",
        "strength": 0.0,
        "sign": 0.0,
        "contribution": 0.0,
        "explanation": "Muestra H2H baja; peso H2H reducido.",
        "category": "reliability"
      }
    ],
    "corners_pick": "OVER 9.5",
    "corners_recommended_pick": "OVER 9.5",
    "corners_base_probability": 0.973224,
    "corners_adjusted_probability": 0.973224,
    "corners_adjustment_amount": 0.0,
    "corners_adjustment_breakdown": [],
    "actual_home_score": 1,
    "actual_away_score": 0,
    "actual_result": "TOL",
    "correct_full_game_base": 1,
    "correct_full_game_adjusted": 1,
    "correct_total_base": 1,
    "correct_total_adjusted": 1,
    "correct_btts_base": 1,
    "correct_btts_adjusted": 1,
    "correct_corners_base": 1,
    "correct_corners_adjusted": 1,
    "actual_full_game_class": 1,
    "fg_prob_away_base": 0.0464890360935491,
    "fg_prob_home_base": 0.9377673057411743,
    "fg_prob_draw_base": 0.015743674308201307,
    "fg_prob_away_adjusted": 0.0686597540872483,
    "fg_prob_home_adjusted": 0.8829963315681685,
    "fg_prob_draw_adjusted": 0.04834391434458337,
    "over_actual": 0,
    "btts_actual": 0,
    "corners_actual": 1
  }
]