[
  {
    "game_id": "401570854",
    "date": "2024-09-27",
    "home_team": "MIN",
    "away_team": "BAL",
    "full_game_pick": "MIN",
    "recommended_pick": "MIN",
    "full_game_tier": "NORMAL",
    "confidence": 54.0,
    "correct_full_game_base": false,
    "correct_full_game_adjusted": false,
    "result_label": "FALLO",
    "moneyline_odds": null,
    "pick_ml_odds": null,
    "odds_details": "No Line",
    "sport": "triple_a",
    "league": "Triple-A",
    "q1_pick": "NRFI",
    "q1_hit": true,
    "q1_conf_pct": 54.6,
    "f5_pick": "BAL",
    "correct_f5": true,
    "f5_conf_pct": 60.4
  },
  {
    "game_id": "401570855",
    "date": "2024-09-27",
    "home_team": "DET",
    "away_team": "CHW",
    "full_game_pick": "DET",
    "recommended_pick": "DET",
    "full_game_tier": "NORMAL",
    "confidence": 50.6,
    "correct_full_game_base": true,
    "correct_full_game_adjusted": true,
    "result_label": "ACIERTO",
    "moneyline_odds": null,
    "pick_ml_odds": null,
    "odds_details": "No Line",
    "sport": "triple_a",
    "league": "Triple-A",
    "q1_pick": "NRFI",
    "q1_hit": true,
    "q1_conf_pct": 54.9,
    "f5_pick": "CHW",
    "correct_f5": false,
    "f5_conf_pct": 59.0
  },
  {
    "game_id": "401570856",
    "date": "2024-09-27",
    "home_team": "CHC",
    "away_team": "CIN",
    "full_game_pick": "CIN",
    "recommended_pick": "CIN",
    "full_game_tier": "NORMAL",
    "confidence": 55.7,
    "correct_full_game_base": false,
    "correct_full_game_adjusted": false,
    "result_label": "FALLO",
    "moneyline_odds": null,
    "pick_ml_odds": null,
    "odds_details": "No Line",
    "sport": "triple_a",
    "league": "Triple-A",
    "q1_pick": "NRFI",
    "q1_hit": true,
    "q1_conf_pct": 53.9,
    "f5_pick": "CIN",
    "correct_f5": false,
    "f5_conf_pct": 59.7
  },
  {
    "game_id": "401570857",
    "date": "2024-09-27",
    "home_team": "CLE",
    "away_team": "HOU",
    "full_game_pick": "CLE",
    "recommended_pick": "CLE",
    "full_game_tier": "NORMAL",
    "confidence": 51.3,
    "correct_full_game_base": false,
    "correct_full_game_adjusted": false,
    "result_label": "FALLO",
    "moneyline_odds": null,
    "pick_ml_odds": null,
    "odds_details": "No Line",
    "sport": "triple_a",
    "league": "Triple-A",
    "q1_pick": "NRFI",
    "q1_hit": false,
    "q1_conf_pct": 55.4,
    "f5_pick": "HOU",
    "correct_f5": true,
    "f5_conf_pct": 64.6
  },
  {
    "game_id": "401570858",
    "date": "2024-09-27",
    "home_team": "ATL",
    "away_team": "KC",
    "full_game_pick": "KC",
    "recommended_pick": "KC",
    "full_game_tier": "NORMAL",
    "confidence": 54.9,
    "correct_full_game_base": false,
    "correct_full_game_adjusted": false,
    "result_label": "FALLO",
    "moneyline_odds": null,
    "pick_ml_odds": null,
    "odds_details": "No Line",
    "sport": "triple_a",
    "league": "Triple-A",
    "q1_pick": "NRFI",
    "q1_hit": true,
    "q1_conf_pct": 54.9,
    "f5_pick": "KC",
    "correct_f5": false,
    "f5_conf_pct": 62.5
  },
  {
    "game_id": "401570859",
    "date": "2024-09-27",
    "home_team": "COL",
    "away_team": "LAD",
    "full_game_pick": "LAD",
    "recommended_pick": "LAD",
    "full_game_tier": "NORMAL",
    "confidence": 58.9,
    "correct_full_game_base": true,
    "correct_full_game_adjusted": true,
    "result_label": "ACIERTO",
    "moneyline_odds": null,
    "pick_ml_odds": null,
    "odds_details": "No Line",
    "sport": "triple_a",
    "league": "Triple-A",
    "q1_pick": "NRFI",
    "q1_hit": false,
    "q1_conf_pct": 54.3,
    "f5_pick": "LAD",
    "correct_f5": true,
    "f5_conf_pct": 65.9
  },
  {
    "game_id": "401570860",
    "date": "2024-09-27",
    "home_team": "TOR",
    "away_team": "MIA",
    "full_game_pick": "MIA",
    "recommended_pick": "MIA",
    "full_game_tier": "NORMAL",
    "confidence": 54.9,
    "correct_full_game_base": true,
    "correct_full_game_adjusted": true,
    "result_label": "ACIERTO",
    "moneyline_odds": null,
    "pick_ml_odds": null,
    "odds_details": "No Line",
    "sport": "triple_a",
    "league": "Triple-A",
    "q1_pick": "NRFI",
    "q1_hit": false,
    "q1_conf_pct": 55.3,
    "f5_pick": "MIA",
    "correct_f5": true,
    "f5_conf_pct": 65.5
  },
  {
    "game_id": "401570861",
    "date": "2024-09-27",
    "home_team": "MIL",
    "away_team": "NYM",
    "full_game_pick": "NYM",
    "recommended_pick": "NYM",
    "full_game_tier": "NORMAL",
    "confidence": 51.3,
    "correct_full_game_base": false,
    "correct_full_game_adjusted": false,
    "result_label": "FALLO",
    "moneyline_odds": null,
    "pick_ml_odds": null,
    "odds_details": "No Line",
    "sport": "triple_a",
    "league": "Triple-A",
    "q1_pick": "NRFI",
    "q1_hit": false,
    "q1_conf_pct": 55.6,
    "f5_pick": "NYM",
    "correct_f5": false,
    "f5_conf_pct": 63.2
  },
  {
    "game_id": "401570862",
    "date": "2024-09-27",
    "home_team": "SEA",
    "away_team": "OAK",
    "full_game_pick": "OAK",
    "recommended_pick": "OAK",
    "full_game_tier": "NORMAL",
    "confidence": 52.4,
    "correct_full_game_base": false,
    "correct_full_game_adjusted": false,
    "result_label": "FALLO",
    "moneyline_odds": null,
    "pick_ml_odds": null,
    "odds_details": "No Line",
    "sport": "triple_a",
    "league": "Triple-A",
    "q1_pick": "NRFI",
    "q1_hit": true,
    "q1_conf_pct": 55.3,
    "f5_pick": "OAK",
    "correct_f5": false,
    "f5_conf_pct": 61.4
  },
  {
    "game_id": "401570863",
    "date": "2024-09-27",
    "home_team": "WSH",
    "away_team": "PHI",
    "full_game_pick": "PHI",
    "recommended_pick": "PHI",
    "full_game_tier": "NORMAL",
    "confidence": 50.0,
    "correct_full_game_base": false,
    "correct_full_game_adjusted": false,
    "result_label": "FALLO",
    "moneyline_odds": null,
    "pick_ml_odds": null,
    "odds_details": "No Line",
    "sport": "triple_a",
    "league": "Triple-A",
    "q1_pick": "NRFI",
    "q1_hit": false,
    "q1_conf_pct": 55.6,
    "f5_pick": "PHI",
    "correct_f5": false,
    "f5_conf_pct": 61.2
  },
  {
    "game_id": "401570864",
    "date": "2024-09-27",
    "home_team": "NYY",
    "away_team": "PIT",
    "full_game_pick": "NYY",
    "recommended_pick": "NYY",
    "full_game_tier": "NORMAL",
    "confidence": 50.9,
    "correct_full_game_base": false,
    "correct_full_game_adjusted": false,
    "result_label": "FALLO",
    "moneyline_odds": null,
    "pick_ml_odds": null,
    "odds_details": "No Line",
    "sport": "triple_a",
    "league": "Triple-A",
    "q1_pick": "NRFI",
    "q1_hit": true,
    "q1_conf_pct": 54.9,
    "f5_pick": "PIT",
    "correct_f5": false,
    "f5_conf_pct": 63.0
  },
  {
    "game_id": "401570865",
    "date": "2024-09-27",
    "home_team": "ARI",
    "away_team": "SD",
    "full_game_pick": "ARI",
    "recommended_pick": "ARI",
    "full_game_tier": "NORMAL",
    "confidence": 57.1,
    "correct_full_game_base": false,
    "correct_full_game_adjusted": false,
    "result_label": "FALLO",
    "moneyline_odds": null,
    "pick_ml_odds": null,
    "odds_details": "No Line",
    "sport": "triple_a",
    "league": "Triple-A",
    "q1_pick": "NRFI",
    "q1_hit": false,
    "q1_conf_pct": 53.9,
    "f5_pick": "SD",
    "correct_f5": true,
    "f5_conf_pct": 62.4
  },
  {
    "game_id": "401570866",
    "date": "2024-09-27",
    "home_team": "SF",
    "away_team": "STL",
    "full_game_pick": "STL",
    "recommended_pick": "STL",
    "full_game_tier": "NORMAL",
    "confidence": 51.0,
    "correct_full_game_base": true,
    "correct_full_game_adjusted": true,
    "result_label": "ACIERTO",
    "moneyline_odds": null,
    "pick_ml_odds": null,
    "odds_details": "No Line",
    "sport": "triple_a",
    "league": "Triple-A",
    "q1_pick": "NRFI",
    "q1_hit": false,
    "q1_conf_pct": 55.7,
    "f5_pick": "STL",
    "correct_f5": true,
    "f5_conf_pct": 63.0
  },
  {
    "game_id": "401570867",
    "date": "2024-09-27",
    "home_team": "BOS",
    "away_team": "TB",
    "full_game_pick": "TB",
    "recommended_pick": "TB",
    "full_game_tier": "NORMAL",
    "confidence": 51.7,
    "correct_full_game_base": true,
    "correct_full_game_adjusted": true,
    "result_label": "ACIERTO",
    "moneyline_odds": null,
    "pick_ml_odds": null,
    "odds_details": "No Line",
    "sport": "triple_a",
    "league": "Triple-A",
    "q1_pick": "NRFI",
    "q1_hit": true,
    "q1_conf_pct": 55.5,
    "f5_pick": "TB",
    "correct_f5": true,
    "f5_conf_pct": 63.7
  },
  {
    "game_id": "401570868",
    "date": "2024-09-27",
    "home_team": "LAA",
    "away_team": "TEX",
    "full_game_pick": "LAA",
    "recommended_pick": "LAA",
    "full_game_tier": "NORMAL",
    "confidence": 54.8,
    "correct_full_game_base": false,
    "correct_full_game_adjusted": false,
    "result_label": "FALLO",
    "moneyline_odds": null,
    "pick_ml_odds": null,
    "odds_details": "No Line",
    "sport": "triple_a",
    "league": "Triple-A",
    "q1_pick": "NRFI",
    "q1_hit": false,
    "q1_conf_pct": 54.6,
    "f5_pick": "TEX",
    "correct_f5": true,
    "f5_conf_pct": 58.8
  }
]